setup.cfg
setup.py
buffer_python.egg-info/PKG-INFO
buffer_python.egg-info/SOURCES.txt
buffer_python.egg-info/dependency_links.txt
buffer_python.egg-info/requires.txt
buffer_python.egg-info/top_level.txt
buffpy/__init__.py
buffpy/api.py
buffpy/response.py
buffpy/test.py