Metadata-Version: 1.1
Name: buffer-python
Version: 1.06
Summary: Python library for Buffer App
Home-page: https://github.com/vtemian/buffpy
Author: Vlad Temian
Author-email: vladtemian@gmail.com
License: UNKNOWN
Platform: any
Classifier: Programming Language :: Python :: 2.7
